[
  {
    "paper_id": 125,
    "paper_title": "What is the future of the internet?",
    "conference": "Amsterdam location VUmc, Netherlands",
    "publish_date": "2020-11-2"
  },
  {
    "paper_id": 126,
    "paper_title": "How did climate change in the last 38 years?",
    "conference": "The Hague Conference Centre New Babylon, Netherlands",
    "publish_date": "2019-01-8"
  },
  {
    "paper_id": 127,
    "paper_title": "Ocean pollution: Unseen tragedies.",
    "conference": "Online, Netherlands",
    "publish_date": "2020-1-8"
  },
  {
    "paper_id": 128,
    "paper_title": "How can creative marketing increase your sales?",
    "conference": "The Hague, Netherlands",
    "publish_date": "2010-2-2"
  },
  {
    "paper_id": 129,
    "paper_title": "Does taxation aim to kill small businesses?",
    "conference": "The Hague Conference Centre New Babylon, Netherlands",
    "publish_date": "202.89-80"
  }
]
